Workbook

Sheet DICIEMBRE
C2: RESUMEN | E2: VENTA PERIODO | F2: NETO | G2: % COSTO VENTA | M2: OP | N2: 0.25 | O2: 0.06 | P2: 0.12 | Q2: 0.03 | R2: 0.02
C3: COMERCIAL | F3: =E3/1.19 | G3: =(N6+O6)/F3
C4: VENTA ACTUAL | M4: IND | N4: =IF(N5>N2,"MAL","BIEN") | O4: =IF(O5>O2,"MAL","BIEN") | P4: =IF(P5>P2,"MAL","BIEN") | Q4: =IF(Q5>Q2,"MAL","BIEN") | R4: =IF(R5>R2,"MAL","BIEN")
C5: COSTO VENTA | D5: =N6+O6 | G5: 24 horas | H5: IVA | I5: TOTAL | M5: % | N5: =N6/F3 | O5: =O6/$F$3 | P5: =P6/$F$3 | Q5: =Q6/$F$3 | R5: =R6/$F$3
C6: % COSTO VENTA | D6: =D5/(D4/1.19) | F6: TOTAL ITEM | G6: =DICIEMBRE!$G$656 | H6: =DICIEMBRE!$H$656 | I6: =DICIEMBRE!$I$656 | M6: T | N6: =N656 | O6: =O656 | P6: =P656 | Q6: =Q656 | R6: =R656
B8: DIA | C8: NUM INT | D8: TIPO | E8: PROVEEDOR | F8: NUM FACTURA | G8: SUB TOTAL | H8: IVA | I8: TOTAL | J8: DETALLE | K8: MEDIO PAGO | L8: N CHEQUE | N8: AL | O8: BA | P8: GF | Q8: OT | R8: AS | T8: Abel leal Burgos | U8: Agricola Mamita Paz | V8: Agricola rosario | W8: Agrosuper | X8: Alca | Y8: ALMACENES PARIS | Z8: American pos | AA8: Arenillas | AB8: Atelier | AC8: Aurelia Quezada | AD8: Bastien | AE8: Bredenmaster | AF8: Buen chef | AG8: Carnes Ñuble | AH8: CCU | AI8: Cencosud | AJ8: Central Mayorista | AK8: Chokko | AL8: Coca Cola Andina | AM8: Com. Inver. Chacabuco | AN8: Decaba | AO8: DELMAR | AP8: Desa | AQ8: DIMERC | AR8: EASY | AS8: el taller | AT8: Europapel | AU8: FBS | AV8: FEDERAL SEGURIDAD | AW8: FHM Alimentos | AX8: Fortunata | AY8: Gazpacho | AZ8: Global Frozen | BA8: Gourmet virtual | BB8: Granarolo | BC8: Guallarauco | BD8: Hielo freeze | BE8: Indusmel | BF8: Inversierra | BG8: Isla del faraon | BH8: Jaime Cesar Farias | BI8: Jose Molina | BJ8: Julia del Carmen | BK8: JUMBO | BL8: KITCHEN CENTER SPA | BM8: La Isla del Faraon | BN8: La Vaquita | BO8: La Vinoteca | BP8: Las Delicias del | BQ8: Las piedras | BR8: licores.cl | BS8: Limpicamp Ltda. | BT8: Los colonos | BU8: Mauro | BV8: Mercado Silvestre | BW8: Miguel | BX8: MIGUEL ANGEL PARRA | BY8: Miguel Gonzalez | BZ8: Mimus | CA8: Modus Vivendi | CB8: Neuchatel S.A. | CC8: Nubox | CD8: P&E | CE8: Pahuilmo | CF8: Palta Mundial | CG8: Panesco | CH8: Papeles Santiago | CI8: PC FACTORY | CJ8: Pedidos de hoy | CK8: Pest free | CL8: PF | CM8: Premium Brands | CN8: Productos galdames | CO8: Punto entrega | CP8: PUNTO PLAST | CQ8: RENATE IWERSEN | CR8: Saint Jacques | CS8: Santa Rita | CT8: Servicefood | CU8: silvestre | CV8: Sociedad agricola | CW8: Sofruco | CX8: Southwind | CY8: SURA | CZ8: Surlat | DA8: VCT
G9: =DICIEMBRE!$I9-DICIEMBRE!$H9 | N9: =IF($D9="AL",$G9,0) | O9: =IF($D9="BA",$G9,0) | P9: =IF($D9="GF",$G9,0) | Q9: =IF($D9="OT",$G9,0) | R9: =IF($D9="AS",$G9,0) | T9: =IF($E9=T$8,$G9,0) | U9: =IF($E9=U$8,$G9,0) | V9: =IF($E9=V$8,$G9,0) | W9: =IF($E9=W$8,$G9,0) | X9: =IF($E9=X$8,$G9,0) | Y9: =IF($E9=Y$8,$G9,0) | Z9: =IF($E9=Z$8,$G9,0) | AA9: =IF($E9=AA$8,$G9,0) | ... DA9: =IF($E9=DA$8,$G9,0)
G10: =DICIEMBRE!$I10-DICIEMBRE!$H10 | N10: =IF($D10="AL",$G10,0) | O10: =IF($D10="BA",$G10,0) | P10: =IF($D10="GF",$G10,0) | Q10: =IF($D10="OT",$G10,0) | R10: =IF($D10="AS",$G10,0) | T10: =IF($E10=T$8,$G10,0) | U10: =IF($E10=U$8,$G10,0) | V10: =IF($E10=V$8,$G10,0) | W10: =IF($E10=W$8,$G10,0) | X10: =IF($E10=X$8,$G10,0) | Y10: =IF($E10=Y$8,$G10,0) | Z10: =IF($E10=Z$8,$G10,0) | AA10: =IF($E10=AA$8,$G10,0) | ... DA10: =IF($E10=DA$8,$G10,0)
G11: =DICIEMBRE!$I11-DICIEMBRE!$H11 | N11: =IF($D11="AL",$G11,0) | O11: =IF($D11="BA",$G11,0) | P11: =IF($D11="GF",$G11,0) | Q11: =IF($D11="OT",$G11,0) | R11: =IF($D11="AS",$G11,0) | T11: =IF($E11=T$8,$G11,0) | U11: =IF($E11=U$8,$G11,0) | V11: =IF($E11=V$8,$G11,0) | W11: =IF($E11=W$8,$G11,0) | X11: =IF($E11=X$8,$G11,0) | Y11: =IF($E11=Y$8,$G11,0) | Z11: =IF($E11=Z$8,$G11,0) | AA11: =IF($E11=AA$8,$G11,0) | ... DA11: =IF($E11=DA$8,$G11,0)
G12: =DICIEMBRE!$I12-DICIEMBRE!$H12 | N12: =IF($D12="AL",$G12,0) | O12: =IF($D12="BA",$G12,0) | P12: =IF($D12="GF",$G12,0) | Q12: =IF($D12="OT",$G12,0) | R12: =IF($D12="AS",$G12,0) | T12: =IF($E12=T$8,$G12,0) | U12: =IF($E12=U$8,$G12,0) | V12: =IF($E12=V$8,$G12,0) | W12: =IF($E12=W$8,$G12,0) | X12: =IF($E12=X$8,$G12,0) | Y12: =IF($E12=Y$8,$G12,0) | Z12: =IF($E12=Z$8,$G12,0) | AA12: =IF($E12=AA$8,$G12,0) | ... DA12: =IF($E12=DA$8,$G12,0)
G13: =DICIEMBRE!$I13-DICIEMBRE!$H13 | N13: =IF($D13="AL",$G13,0) | O13: =IF($D13="BA",$G13,0) | P13: =IF($D13="GF",$G13,0) | Q13: =IF($D13="OT",$G13,0) | R13: =IF($D13="AS",$G13,0) | T13: =IF($E13=T$8,$G13,0) | U13: =IF($E13=U$8,$G13,0) | V13: =IF($E13=V$8,$G13,0) | W13: =IF($E13=W$8,$G13,0) | X13: =IF($E13=X$8,$G13,0) | Y13: =IF($E13=Y$8,$G13,0) | Z13: =IF($E13=Z$8,$G13,0) | AA13: =IF($E13=AA$8,$G13,0) | ... DA13: =IF($E13=DA$8,$G13,0)
G14: =DICIEMBRE!$I14-DICIEMBRE!$H14 | N14: =IF($D14="AL",$G14,0) | O14: =IF($D14="BA",$G14,0) | P14: =IF($D14="GF",$G14,0) | Q14: =IF($D14="OT",$G14,0) | R14: =IF($D14="AS",$G14,0) | T14: =IF($E14=T$8,$G14,0) | U14: =IF($E14=U$8,$G14,0) | V14: =IF($E14=V$8,$G14,0) | W14: =IF($E14=W$8,$G14,0) | X14: =IF($E14=X$8,$G14,0) | Y14: =IF($E14=Y$8,$G14,0) | Z14: =IF($E14=Z$8,$G14,0) | AA14: =IF($E14=AA$8,$G14,0) | ... DA14: =IF($E14=DA$8,$G14,0)
G15: =DICIEMBRE!$I15-DICIEMBRE!$H15 | N15: =IF($D15="AL",$G15,0) | O15: =IF($D15="BA",$G15,0) | P15: =IF($D15="GF",$G15,0) | Q15: =IF($D15="OT",$G15,0) | R15: =IF($D15="AS",$G15,0) | T15: =IF($E15=T$8,$G15,0) | U15: =IF($E15=U$8,$G15,0) | V15: =IF($E15=V$8,$G15,0) | W15: =IF($E15=W$8,$G15,0) | X15: =IF($E15=X$8,$G15,0) | Y15: =IF($E15=Y$8,$G15,0) | Z15: =IF($E15=Z$8,$G15,0) | AA15: =IF($E15=AA$8,$G15,0) | ... DA15: =IF($E15=DA$8,$G15,0)
G16: =DICIEMBRE!$I16-DICIEMBRE!$H16 | N16: =IF($D16="AL",$G16,0) | O16: =IF($D16="BA",$G16,0) | P16: =IF($D16="GF",$G16,0) | Q16: =IF($D16="OT",$G16,0) | R16: =IF($D16="AS",$G16,0) | T16: =IF($E16=T$8,$G16,0) | U16: =IF($E16=U$8,$G16,0) | V16: =IF($E16=V$8,$G16,0) | W16: =IF($E16=W$8,$G16,0) | X16: =IF($E16=X$8,$G16,0) | Y16: =IF($E16=Y$8,$G16,0) | Z16: =IF($E16=Z$8,$G16,0) | AA16: =IF($E16=AA$8,$G16,0) | ... DA16: =IF($E16=DA$8,$G16,0)
G17: =DICIEMBRE!$I17-DICIEMBRE!$H17 | N17: =IF($D17="AL",$G17,0) | O17: =IF($D17="BA",$G17,0) | P17: =IF($D17="GF",$G17,0) | Q17: =IF($D17="OT",$G17,0) | R17: =IF($D17="AS",$G17,0) | T17: =IF($E17=T$8,$G17,0) | U17: =IF($E17=U$8,$G17,0) | V17: =IF($E17=V$8,$G17,0) | W17: =IF($E17=W$8,$G17,0) | X17: =IF($E17=X$8,$G17,0) | Y17: =IF($E17=Y$8,$G17,0) | Z17: =IF($E17=Z$8,$G17,0) | AA17: =IF($E17=AA$8,$G17,0) | ... DA17: =IF($E17=DA$8,$G17,0)
G18: =DICIEMBRE!$I18-DICIEMBRE!$H18 | N18: =IF($D18="AL",$G18,0) | O18: =IF($D18="BA",$G18,0) | P18: =IF($D18="GF",$G18,0) | Q18: =IF($D18="OT",$G18,0) | R18: =IF($D18="AS",$G18,0) | T18: =IF($E18=T$8,$G18,0) | U18: =IF($E18=U$8,$G18,0) | V18: =IF($E18=V$8,$G18,0) | W18: =IF($E18=W$8,$G18,0) | X18: =IF($E18=X$8,$G18,0) | Y18: =IF($E18=Y$8,$G18,0) | Z18: =IF($E18=Z$8,$G18,0) | AA18: =IF($E18=AA$8,$G18,0) | ... DA18: =IF($E18=DA$8,$G18,0)
G19: =DICIEMBRE!$I19-DICIEMBRE!$H19 | N19: =IF($D19="AL",$G19,0) | O19: =IF($D19="BA",$G19,0) | P19: =IF($D19="GF",$G19,0) | Q19: =IF($D19="OT",$G19,0) | R19: =IF($D19="AS",$G19,0) | T19: =IF($E19=T$8,$G19,0) | U19: =IF($E19=U$8,$G19,0) | V19: =IF($E19=V$8,$G19,0) | W19: =IF($E19=W$8,$G19,0) | X19: =IF($E19=X$8,$G19,0) | Y19: =IF($E19=Y$8,$G19,0) | Z19: =IF($E19=Z$8,$G19,0) | AA19: =IF($E19=AA$8,$G19,0) | ... DA19: =IF($E19=DA$8,$G19,0)
G20: =DICIEMBRE!$I20-DICIEMBRE!$H20 | N20: =IF($D20="AL",$G20,0) | O20: =IF($D20="BA",$G20,0) | P20: =IF($D20="GF",$G20,0) | Q20: =IF($D20="OT",$G20,0) | R20: =IF($D20="AS",$G20,0) | T20: =IF($E20=T$8,$G20,0) | U20: =IF($E20=U$8,$G20,0) | V20: =IF($E20=V$8,$G20,0) | W20: =IF($E20=W$8,$G20,0) | X20: =IF($E20=X$8,$G20,0) | Y20: =IF($E20=Y$8,$G20,0) | Z20: =IF($E20=Z$8,$G20,0) | AA20: =IF($E20=AA$8,$G20,0) | ... DA20: =IF($E20=DA$8,$G20,0)
... G285: =DICIEMBRE!$I285-DICIEMBRE!$H285 | N285: =IF($D285="AL",$G285,0) | O285: =IF($D285="BA",$G285,0) | P285: =IF($D285="GF",$G285,0) | Q285: =IF($D285="OT",$G285,0) | R285: =IF($D285="AS",$G285,0) | T285: =IF($E285=T$8,$G285,0) | U285: =IF($E285=U$8,$G285,0) | V285: =IF($E285=V$8,$G285,0) | W285: =IF($E285=W$8,$G285,0) | X285: =IF($E285=X$8,$G285,0) | Y285: =IF($E285=Y$8,$G285,0) | Z285: =IF($E285=Z$8,$G285,0) | AA285: =IF($E285=AA$8,$G285,0) | ... DA285: =IF($E285=DA$8,$G285,0)
G286: =DICIEMBRE!$I286-DICIEMBRE!$H286 | N286: =IF($G286="AL",$G286,0) | O286: =IF($G286="BA",$G286,0) | P286: =IF($G286="GF",$G286,0) | Q286: =IF($G286="OT",$G286,0) | R286: =IF($G286="AS",$G286,0) | T286: =IF($E286=T$8,$G286,0) | U286: =IF($E286=U$8,$G286,0) | V286: =IF($E286=V$8,$G286,0) | W286: =IF($E286=W$8,$G286,0) | X286: =IF($E286=X$8,$G286,0) | Y286: =IF($E286=Y$8,$G286,0) | Z286: =IF($E286=Z$8,$G286,0) | AA286: =IF($E286=AA$8,$G286,0) | ... DA286: =IF($E286=DA$8,$G286,0)
G287: =DICIEMBRE!$I287-DICIEMBRE!$H287 | N287: =IF($D286="AL",$G287,0) | O287: =IF($D286="BA",$G287,0) | P287: =IF($D286="GF",$G287,0) | Q287: =IF($D286="OT",$G287,0) | R287: =IF($D286="AS",$G287,0) | T287: =IF($E287=T$8,$G287,0) | U287: =IF($E287=U$8,$G287,0) | V287: =IF($E287=V$8,$G287,0) | W287: =IF($E287=W$8,$G287,0) | X287: =IF($E287=X$8,$G287,0) | Y287: =IF($E287=Y$8,$G287,0) | Z287: =IF($E287=Z$8,$G287,0) | AA287: =IF($E287=AA$8,$G287,0) | ... DA287: =IF($E287=DA$8,$G287,0)
G288: =DICIEMBRE!$I288-DICIEMBRE!$H288 | N288: =IF($D288="AL",$G288,0) | O288: =IF($D288="BA",$G288,0) | P288: =IF($D288="GF",$G288,0) | Q288: =IF($D288="OT",$G288,0) | R288: =IF($D288="AS",$G288,0) | T288: =IF($E288=T$8,$G288,0) | U288: =IF($E288=U$8,$G288,0) | V288: =IF($E288=V$8,$G288,0) | W288: =IF($E288=W$8,$G288,0) | X288: =IF($E288=X$8,$G288,0) | Y288: =IF($E288=Y$8,$G288,0) | Z288: =IF($E288=Z$8,$G288,0) | AA288: =IF($E288=AA$8,$G288,0) | ... DA288: =IF($E288=DA$8,$G288,0)
G289: =DICIEMBRE!$I289-DICIEMBRE!$H289 | N289: =IF($D289="AL",$G289,0) | O289: =IF($D289="BA",$G289,0) | P289: =IF($D289="GF",$G289,0) | Q289: =IF($D289="OT",$G289,0) | R289: =IF($D289="AS",$G289,0) | T289: =IF($E289=T$8,$G289,0) | U289: =IF($E289=U$8,$G289,0) | V289: =IF($E289=V$8,$G289,0) | W289: =IF($E289=W$8,$G289,0) | X289: =IF($E289=X$8,$G289,0) | Y289: =IF($E289=Y$8,$G289,0) | Z289: =IF($E289=Z$8,$G289,0) | AA289: =IF($E289=AA$8,$G289,0) | ... DA289: =IF($E289=DA$8,$G289,0)
G290: =DICIEMBRE!$I290-DICIEMBRE!$H290 | N290: =IF($D290="AL",$G290,0) | O290: =IF($D290="BA",$G290,0) | P290: =IF($D290="GF",$G290,0) | Q290: =IF($D290="OT",$G290,0) | R290: =IF($D290="AS",$G290,0) | T290: =IF($E290=T$8,$G290,0) | U290: =IF($E290=U$8,$G290,0) | V290: =IF($E290=V$8,$G290,0) | W290: =IF($E290=W$8,$G290,0) | X290: =IF($E290=X$8,$G290,0) | Y290: =IF($E290=Y$8,$G290,0) | Z290: =IF($E290=Z$8,$G290,0) | AA290: =IF($E290=AA$8,$G290,0) | ... DA290: =IF($E290=DA$8,$G290,0)
G291: =DICIEMBRE!$I291-DICIEMBRE!$H291 | N291: =IF($D291="AL",$G291,0) | O291: =IF($D291="BA",$G291,0) | P291: =IF($D291="GF",$G291,0) | Q291: =IF($D291="OT",$G291,0) | R291: =IF($D291="AS",$G291,0) | T291: =IF($E291=T$8,$G291,0) | U291: =IF($E291=U$8,$G291,0) | V291: =IF($E291=V$8,$G291,0) | W291: =IF($E291=W$8,$G291,0) | X291: =IF($E291=X$8,$G291,0) | Y291: =IF($E291=Y$8,$G291,0) | Z291: =IF($E291=Z$8,$G291,0) | AA291: =IF($E291=AA$8,$G291,0) | ... DA291: =IF($E291=DA$8,$G291,0)
G292: =DICIEMBRE!$I292-DICIEMBRE!$H292 | N292: =IF($D292="AL",$G292,0) | O292: =IF($D292="BA",$G292,0) | P292: =IF($D292="GF",$G292,0) | Q292: =IF($D292="OT",$G292,0) | R292: =IF($D292="AS",$G292,0) | T292: =IF($E292=T$8,$G292,0) | U292: =IF($E292=U$8,$G292,0) | V292: =IF($E292=V$8,$G292,0) | W292: =IF($E292=W$8,$G292,0) | X292: =IF($E292=X$8,$G292,0) | Y292: =IF($E292=Y$8,$G292,0) | Z292: =IF($E292=Z$8,$G292,0) | AA292: =IF($E292=AA$8,$G292,0) | ... DA292: =IF($E292=DA$8,$G292,0)
G293: =DICIEMBRE!$I293-DICIEMBRE!$H293 | N293: =IF($D293="AL",$G293,0) | O293: =IF($D293="BA",$G293,0) | P293: =IF($D293="GF",$G293,0) | Q293: =IF($D293="OT",$G293,0) | R293: =IF($D293="AS",$G293,0) | T293: =IF($E293=T$8,$G293,0) | U293: =IF($E293=U$8,$G293,0) | V293: =IF($E293=V$8,$G293,0) | W293: =IF($E293=W$8,$G293,0) | X293: =IF($E293=X$8,$G293,0) | Y293: =IF($E293=Y$8,$G293,0) | Z293: =IF($E293=Z$8,$G293,0) | AA293: =IF($E293=AA$8,$G293,0) | ... DA293: =IF($E293=DA$8,$G293,0)
G294: =DICIEMBRE!$I294-DICIEMBRE!$H294 | N294: =IF($D294="AL",$G294,0) | O294: =IF($D294="BA",$G294,0) | P294: =IF($D294="GF",$G294,0) | Q294: =IF($D294="OT",$G294,0) | R294: =IF($D294="AS",$G294,0) | T294: =IF($E294=T$8,$G294,0) | U294: =IF($E294=U$8,$G294,0) | V294: =IF($E294=V$8,$G294,0) | W294: =IF($E294=W$8,$G294,0) | X294: =IF($E294=X$8,$G294,0) | Y294: =IF($E294=Y$8,$G294,0) | Z294: =IF($E294=Z$8,$G294,0) | AA294: =IF($E294=AA$8,$G294,0) | ... DA294: =IF($E294=DA$8,$G294,0)
G295: =DICIEMBRE!$I295-DICIEMBRE!$H295 | N295: =IF($D295="AL",$G295,0) | O295: =IF($D295="BA",$G295,0) | P295: =IF($D295="GF",$G295,0) | Q295: =IF($D295="OT",$G295,0) | R295: =IF($D295="AS",$G295,0) | T295: =IF($E295=T$8,$G295,0) | U295: =IF($E295=U$8,$G295,0) | V295: =IF($E295=V$8,$G295,0) | W295: =IF($E295=W$8,$G295,0) | X295: =IF($E295=X$8,$G295,0) | Y295: =IF($E295=Y$8,$G295,0) | Z295: =IF($E295=Z$8,$G295,0) | AA295: =IF($E295=AA$8,$G295,0) | ... DA295: =IF($E295=DA$8,$G295,0)
G296: =DICIEMBRE!$I296-DICIEMBRE!$H296 | N296: =IF($D296="AL",$G296,0) | O296: =IF($D296="BA",$G296,0) | P296: =IF($D296="GF",$G296,0) | Q296: =IF($D296="OT",$G296,0) | R296: =IF($D296="AS",$G296,0) | T296: =IF($E296=T$8,$G296,0) | U296: =IF($E296=U$8,$G296,0) | V296: =IF($E296=V$8,$G296,0) | W296: =IF($E296=W$8,$G296,0) | X296: =IF($E296=X$8,$G296,0) | Y296: =IF($E296=Y$8,$G296,0) | Z296: =IF($E296=Z$8,$G296,0) | AA296: =IF($E296=AA$8,$G296,0) | ... DA296: =IF($E296=DA$8,$G296,0)
G297: =DICIEMBRE!$I297-DICIEMBRE!$H297 | N297: =IF($D297="AL",$G297,0) | O297: =IF($D297="BA",$G297,0) | P297: =IF($D297="GF",$G297,0) | Q297: =IF($D297="OT",$G297,0) | R297: =IF($D297="AS",$G297,0) | T297: =IF($E297=T$8,$G297,0) | U297: =IF($E297=U$8,$G297,0) | V297: =IF($E297=V$8,$G297,0) | W297: =IF($E297=W$8,$G297,0) | X297: =IF($E297=X$8,$G297,0) | Y297: =IF($E297=Y$8,$G297,0) | Z297: =IF($E297=Z$8,$G297,0) | AA297: =IF($E297=AA$8,$G297,0) | ... DA297: =IF($E297=DA$8,$G297,0)
G298: =DICIEMBRE!$I298-DICIEMBRE!$H298 | N298: =IF($D298="AL",$G298,0) | O298: =IF($D298="BA",$G298,0) | P298: =IF($D298="GF",$G298,0) | Q298: =IF($D298="OT",$G298,0) | R298: =IF($D298="AS",$G298,0) | T298: =IF($E298=T$8,$G298,0) | U298: =IF($E298=U$8,$G298,0) | V298: =IF($E298=V$8,$G298,0) | W298: =IF($E298=W$8,$G298,0) | X298: =IF($E298=X$8,$G298,0) | Y298: =IF($E298=Y$8,$G298,0) | Z298: =IF($E298=Z$8,$G298,0) | AA298: =IF($E298=AA$8,$G298,0) | ... DA298: =IF($E298=DA$8,$G298,0)
G299: =DICIEMBRE!$I299-DICIEMBRE!$H299 | N299: =IF($D299="AL",$G299,0) | O299: =IF($D299="BA",$G299,0) | P299: =IF($D299="GF",$G299,0) | Q299: =IF($D299="OT",$G299,0) | R299: =IF($D299="AS",$G299,0) | T299: =IF($E299=T$8,$G299,0) | U299: =IF($E299=U$8,$G299,0) | V299: =IF($E299=V$8,$G299,0) | W299: =IF($E299=W$8,$G299,0) | X299: =IF($E299=X$8,$G299,0) | Y299: =IF($E299=Y$8,$G299,0) | Z299: =IF($E299=Z$8,$G299,0) | AA299: =IF($E299=AA$8,$G299,0) | ... DA299: =IF($E299=DA$8,$G299,0)
... G655: =DICIEMBRE!$I655-DICIEMBRE!$H655 | N655: =IF($D655="AL",$G655,0) | O655: =IF($D655="BA",$G655,0) | P655: =IF($D655="GF",$G655,0) | Q655: =IF($D655="OT",$G655,0) | R655: =IF($D655="AS",$G655,0) | T655: =IF($E655=T$8,$G655,0) | U655: =IF($E655=U$8,$G655,0) | V655: =IF($E655=V$8,$G655,0) | W655: =IF($E655=W$8,$G655,0) | X655: =IF($E655=X$8,$G655,0) | Y655: =IF($E655=Y$8,$G655,0) | Z655: =IF($E655=Z$8,$G655,0) | AA655: =IF($E655=AA$8,$G655,0) | ... DA655: =IF($E655=DA$8,$G655,0)
B656: Total | G656: =SUBTOTAL(109,DICIEMBRE!$G$9:$G$655) | H656: =SUBTOTAL(109,DICIEMBRE!$H$9:$H$655) | I656: =SUBTOTAL(109,DICIEMBRE!$I$9:$I$655) | N656: =SUM(N9:N655) | O656: =SUM(O9:O655) | P656: =SUM(P9:P655) | Q656: =SUM(Q9:Q655) | R656: =SUM(R9:R655) | T656: =SUM(T9:T655) | U656: =SUM(U9:U655) | V656: =SUM(V9:V655) | W656: =SUM(W9:W655) | X656: =SUM(X9:X655) | Y656: =SUM(Y9:Y655) | Z656: =SUM(Z9:Z655) | AA656: =SUM(AA9:AA655) | ... DA656: =SUM(DA9:DA655) | DB656: =SUM(T656:DA656)
R657: =R656+Q656+P656+O656+N656
B659: ESTADO
B660: =IF(DICIEMBRE!$G$656=R657,"BIEN","MAL")
B661: =IF(DICIEMBRE!$G$656=DB656,"BIEN","MAL")
