Workbook

Sheet MARZO
C2: RESUMEN | D2: RESUMEN | E2: VENTA PERIODO | F2: NETO | G2: % COSTO VENTA | M2: OP | N2: 0.25 | O2: 0.06 | P2: 0.12 | Q2: 0.03 | R2: 0.02
C3: COMERCIAL | D3: COMERCIAL | F3: =E3/1.19 | G3: =(N6+O6)/F3
C4: VENTA ACTUAL | M4: IND | N4: =IF(N5>N2,"MAL","BIEN") | O4: =IF(O5>O2,"MAL","BIEN") | P4: =IF(P5>P2,"MAL","BIEN") | Q4: =IF(Q5>Q2,"MAL","BIEN") | R4: =IF(R5>R2,"MAL","BIEN")
C5: COSTO VENTA | D5: =N6+O6 | G5: 24 horas | H5: IVA | I5: TOTAL | M5: % | N5: =N6/F3 | O5: =O6/$F$3 | P5: =P6/$F$3 | Q5: =Q6/$F$3 | R5: =R6/$F$3
C6: % COSTO VENTA | D6: =D5/(D4/1.19) | F6: TOTAL ITEM | G6: =MARZO!$G$655 | H6: =MARZO!$H$655 | I6: =MARZO!$I$655 | M6: T | N6: =N656 | O6: =O656 | P6: =P656 | Q6: =Q656 | R6: =R656
B8: DIA | C8: NUM INT | D8: TIPO | E8: PROVEEDOR | F8: NUM FACTURA | G8: SUB TOTAL | H8: IVA | I8: TOTAL | J8: DETALLE | K8: MEDIO PAGO | L8: N CHEQUE | N8: AL | O8: BA | P8: GF | Q8: OT | R8: AS | T8: Abel leal Burgos | U8: Agricola Mamita Paz | V8: Agricola rosario | W8: Agrosuper | X8: Alca | Y8: ALMACENES PARIS | Z8: American pos | AA8: Arenillas | AB8: Atelier | AC8: Aurelia Quezada | AD8: Bastien | AE8: Bredenmaster | AF8: Buen chef | AG8: Carnes Ñuble | AH8: CCU | AI8: Cencosud | AJ8: Central Mayorista | AK8: Chokko | AL8: Coca Cola Andina | AM8: Com. Inver. Chacabuco | AN8: Decaba | AO8: DELMAR | AP8: Desa | AQ8: DIMERC | AR8: EASY | AS8: el taller | AT8: Europapel | AU8: FBS | AV8: FEDERAL SEGURIDAD | AW8: FHM Alimentos | AX8: Fortunata | AY8: Gazpacho | AZ8: Global Frozen | BA8: Gourmet virtual | BB8: Granarolo | BC8: Guallarauco | BD8: Hielo freeze | BE8: Indusmel | BF8: Inversierra | BG8: Isla del faraon | BH8: Jaime Cesar Farias | BI8: Jose Molina | BJ8: Julia del Carmen | BK8: JUMBO | BL8: KITCHEN CENTER SPA | BM8: La Isla del Faraon | BN8: La Vaquita | BO8: La Vinoteca | BP8: Las Delicias del | BQ8: Las piedras | BR8: licores.cl | BS8: Limpicamp Ltda. | BT8: Los colonos | BU8: Mauro | BV8: Mercado Silvestre | BW8: Miguel | BX8: MIGUEL ANGEL PARRA | BY8: Miguel Gonzalez | BZ8: Mimus | CA8: Modus Vivendi | CB8: Neuchatel S.A. | CC8: Nubox | CD8: P&E | CE8: Pahuilmo | CF8: Palta Mundial | CG8: Panesco | CH8: Papeles Santiago | CI8: PC FACTORY | CJ8: Pedidos de hoy | CK8: Pest free | CL8: PF | CM8: Premium Brands | CN8: Productos galdames | CO8: Punto entrega | CP8: PUNTO PLAST | CQ8: RENATE IWERSEN | CR8: Saint Jacques | CS8: Santa Rita | CT8: Servicefood | CU8: silvestre | CV8: Sociedad agricola | CW8: Sofruco | CX8: Southwind | CY8: SURA | CZ8: Surlat | DA8: VCT
G9: =MARZO!$I9-MARZO!$H9 | N9: =IF($D9="AL",$G9,0) | O9: =IF($D9="BA",$G9,0) | P9: =IF($D9="GF",$G9,0) | Q9: =IF($D9="OT",$G9,0) | R9: =IF($D9="AS",$G9,0) | T9: =IF($E9=T$8,$G9,0) | U9: =IF($E9=U$8,$G9,0) | V9: =IF($E9=V$8,$G9,0) | W9: =IF($E9=W$8,$G9,0) | X9: =IF($E9=X$8,$G9,0) | Y9: =IF($E9=Y$8,$G9,0) | Z9: =IF($E9=Z$8,$G9,0) | AA9: =IF($E9=AA$8,$G9,0) | ... DA9: =IF($E9=DA$8,$G9,0)
G10: =MARZO!$I10-MARZO!$H10 | N10: =IF($D10="AL",$G10,0) | O10: =IF($D10="BA",$G10,0) | P10: =IF($D10="GF",$G10,0) | Q10: =IF($D10="OT",$G10,0) | R10: =IF($D10="AS",$G10,0) | T10: =IF($E10=T$8,$G10,0) | U10: =IF($E10=U$8,$G10,0) | V10: =IF($E10=V$8,$G10,0) | W10: =IF($E10=W$8,$G10,0) | X10: =IF($E10=X$8,$G10,0) | Y10: =IF($E10=Y$8,$G10,0) | Z10: =IF($E10=Z$8,$G10,0) | AA10: =IF($E10=AA$8,$G10,0) | ... DA10: =IF($E10=DA$8,$G10,0)
G11: =MARZO!$I11-MARZO!$H11 | N11: =IF($D11="AL",$G11,0) | O11: =IF($D11="BA",$G11,0) | P11: =IF($D11="GF",$G11,0) | Q11: =IF($D11="OT",$G11,0) | R11: =IF($D11="AS",$G11,0) | T11: =IF($E11=T$8,$G11,0) | U11: =IF($E11=U$8,$G11,0) | V11: =IF($E11=V$8,$G11,0) | W11: =IF($E11=W$8,$G11,0) | X11: =IF($E11=X$8,$G11,0) | Y11: =IF($E11=Y$8,$G11,0) | Z11: =IF($E11=Z$8,$G11,0) | AA11: =IF($E11=AA$8,$G11,0) | ... DA11: =IF($E11=DA$8,$G11,0)
G12: =MARZO!$I12-MARZO!$H12 | N12: =IF($D12="AL",$G12,0) | O12: =IF($D12="BA",$G12,0) | P12: =IF($D12="GF",$G12,0) | Q12: =IF($D12="OT",$G12,0) | R12: =IF($D12="AS",$G12,0) | T12: =IF($E12=T$8,$G12,0) | U12: =IF($E12=U$8,$G12,0) | V12: =IF($E12=V$8,$G12,0) | W12: =IF($E12=W$8,$G12,0) | X12: =IF($E12=X$8,$G12,0) | Y12: =IF($E12=Y$8,$G12,0) | Z12: =IF($E12=Z$8,$G12,0) | AA12: =IF($E12=AA$8,$G12,0) | ... DA12: =IF($E12=DA$8,$G12,0)
G13: =MARZO!$I13-MARZO!$H13 | N13: =IF($D13="AL",$G13,0) | O13: =IF($D13="BA",$G13,0) | P13: =IF($D13="GF",$G13,0) | Q13: =IF($D13="OT",$G13,0) | R13: =IF($D13="AS",$G13,0) | T13: =IF($E13=T$8,$G13,0) | U13: =IF($E13=U$8,$G13,0) | V13: =IF($E13=V$8,$G13,0) | W13: =IF($E13=W$8,$G13,0) | X13: =IF($E13=X$8,$G13,0) | Y13: =IF($E13=Y$8,$G13,0) | Z13: =IF($E13=Z$8,$G13,0) | AA13: =IF($E13=AA$8,$G13,0) | ... DA13: =IF($E13=DA$8,$G13,0)
G14: =MARZO!$I14-MARZO!$H14 | N14: =IF($D14="AL",$G14,0) | O14: =IF($D14="BA",$G14,0) | P14: =IF($D14="GF",$G14,0) | Q14: =IF($D14="OT",$G14,0) | R14: =IF($D14="AS",$G14,0) | T14: =IF($E14=T$8,$G14,0) | U14: =IF($E14=U$8,$G14,0) | V14: =IF($E14=V$8,$G14,0) | W14: =IF($E14=W$8,$G14,0) | X14: =IF($E14=X$8,$G14,0) | Y14: =IF($E14=Y$8,$G14,0) | Z14: =IF($E14=Z$8,$G14,0) | AA14: =IF($E14=AA$8,$G14,0) | ... DA14: =IF($E14=DA$8,$G14,0)
G15: =MARZO!$I15-MARZO!$H15 | N15: =IF($D15="AL",$G15,0) | O15: =IF($D15="BA",$G15,0) | P15: =IF($D15="GF",$G15,0) | Q15: =IF($D15="OT",$G15,0) | R15: =IF($D15="AS",$G15,0) | T15: =IF($E15=T$8,$G15,0) | U15: =IF($E15=U$8,$G15,0) | V15: =IF($E15=V$8,$G15,0) | W15: =IF($E15=W$8,$G15,0) | X15: =IF($E15=X$8,$G15,0) | Y15: =IF($E15=Y$8,$G15,0) | Z15: =IF($E15=Z$8,$G15,0) | AA15: =IF($E15=AA$8,$G15,0) | ... DA15: =IF($E15=DA$8,$G15,0)
G16: =MARZO!$I16-MARZO!$H16 | N16: =IF($D16="AL",$G16,0) | O16: =IF($D16="BA",$G16,0) | P16: =IF($D16="GF",$G16,0) | Q16: =IF($D16="OT",$G16,0) | R16: =IF($D16="AS",$G16,0) | T16: =IF($E16=T$8,$G16,0) | U16: =IF($E16=U$8,$G16,0) | V16: =IF($E16=V$8,$G16,0) | W16: =IF($E16=W$8,$G16,0) | X16: =IF($E16=X$8,$G16,0) | Y16: =IF($E16=Y$8,$G16,0) | Z16: =IF($E16=Z$8,$G16,0) | AA16: =IF($E16=AA$8,$G16,0) | ... DA16: =IF($E16=DA$8,$G16,0)
G17: =MARZO!$I17-MARZO!$H17 | N17: =IF($D17="AL",$G17,0) | O17: =IF($D17="BA",$G17,0) | P17: =IF($D17="GF",$G17,0) | Q17: =IF($D17="OT",$G17,0) | R17: =IF($D17="AS",$G17,0) | T17: =IF($E17=T$8,$G17,0) | U17: =IF($E17=U$8,$G17,0) | V17: =IF($E17=V$8,$G17,0) | W17: =IF($E17=W$8,$G17,0) | X17: =IF($E17=X$8,$G17,0) | Y17: =IF($E17=Y$8,$G17,0) | Z17: =IF($E17=Z$8,$G17,0) | AA17: =IF($E17=AA$8,$G17,0) | ... DA17: =IF($E17=DA$8,$G17,0)
G18: =MARZO!$I18-MARZO!$H18 | N18: =IF($D18="AL",$G18,0) | O18: =IF($D18="BA",$G18,0) | P18: =IF($D18="GF",$G18,0) | Q18: =IF($D18="OT",$G18,0) | R18: =IF($D18="AS",$G18,0) | T18: =IF($E18=T$8,$G18,0) | U18: =IF($E18=U$8,$G18,0) | V18: =IF($E18=V$8,$G18,0) | W18: =IF($E18=W$8,$G18,0) | X18: =IF($E18=X$8,$G18,0) | Y18: =IF($E18=Y$8,$G18,0) | Z18: =IF($E18=Z$8,$G18,0) | AA18: =IF($E18=AA$8,$G18,0) | ... DA18: =IF($E18=DA$8,$G18,0)
G19: =MARZO!$I19-MARZO!$H19 | N19: =IF($D19="AL",$G19,0) | O19: =IF($D19="BA",$G19,0) | P19: =IF($D19="GF",$G19,0) | Q19: =IF($D19="OT",$G19,0) | R19: =IF($D19="AS",$G19,0) | T19: =IF($E19=T$8,$G19,0) | U19: =IF($E19=U$8,$G19,0) | V19: =IF($E19=V$8,$G19,0) | W19: =IF($E19=W$8,$G19,0) | X19: =IF($E19=X$8,$G19,0) | Y19: =IF($E19=Y$8,$G19,0) | Z19: =IF($E19=Z$8,$G19,0) | AA19: =IF($E19=AA$8,$G19,0) | ... DA19: =IF($E19=DA$8,$G19,0)
G20: =MARZO!$I20-MARZO!$H20 | N20: =IF($D20="AL",$G20,0) | O20: =IF($D20="BA",$G20,0) | P20: =IF($D20="GF",$G20,0) | Q20: =IF($D20="OT",$G20,0) | R20: =IF($D20="AS",$G20,0) | T20: =IF($E20=T$8,$G20,0) | U20: =IF($E20=U$8,$G20,0) | V20: =IF($E20=V$8,$G20,0) | W20: =IF($E20=W$8,$G20,0) | X20: =IF($E20=X$8,$G20,0) | Y20: =IF($E20=Y$8,$G20,0) | Z20: =IF($E20=Z$8,$G20,0) | AA20: =IF($E20=AA$8,$G20,0) | ... DA20: =IF($E20=DA$8,$G20,0)
... G336: =MARZO!$I336-MARZO!$H336 | N336: =IF($D336="AL",$G336,0) | O336: =IF($D336="BA",$G336,0) | P336: =IF($D336="GF",$G336,0) | Q336: =IF($D336="OT",$G336,0) | R336: =IF($D336="AS",$G336,0) | T336: =IF($E336=T$8,$G336,0) | U336: =IF($E336=U$8,$G336,0) | V336: =IF($E336=V$8,$G336,0) | W336: =IF($E336=W$8,$G336,0) | X336: =IF($E336=X$8,$G336,0) | Y336: =IF($E336=Y$8,$G336,0) | Z336: =IF($E336=Z$8,$G336,0) | AA336: =IF($E336=AA$8,$G336,0) | ... DA336: =IF($E336=DA$8,$G336,0)
G337: =MARZO!$I337-MARZO!$H337 | N337: =IF($G337="AL",$G337,0) | O337: =IF($G337="AL",$G337,0) | P337: =IF($G337="AL",$G337,0) | Q337: =IF($G337="AL",$G337,0) | R337: =IF($G337="AL",$G337,0)
G338: =MARZO!$I338-MARZO!$H338 | N338: =IF($D337="AL",$G337,0) | O338: =IF($D337="BA",$G337,0) | P338: =IF($D337="GF",$G337,0) | Q338: =IF($D337="OT",$G337,0) | R338: =IF($D337="AS",$G337,0) | T338: =IF($E337=T$8,$G337,0) | U338: =IF($E337=U$8,$G337,0) | V338: =IF($E337=V$8,$G337,0) | W338: =IF($E337=W$8,$G337,0) | X338: =IF($E337=X$8,$G337,0) | Y338: =IF($E337=Y$8,$G337,0) | Z338: =IF($E337=Z$8,$G337,0) | AA338: =IF($E337=AA$8,$G337,0) | ... DA338: =IF($E337=DA$8,$G337,0)
G339: =MARZO!$I339-MARZO!$H339 | N339: =IF($D338="AL",$G338,0) | O339: =IF($D338="BA",$G338,0) | P339: =IF($D338="GF",$G338,0) | Q339: =IF($D338="OT",$G338,0) | R339: =IF($D338="AS",$G338,0) | T339: =IF($E338=T$8,$G338,0) | U339: =IF($E338=U$8,$G338,0) | V339: =IF($E338=V$8,$G338,0) | W339: =IF($E338=W$8,$G338,0) | X339: =IF($E338=X$8,$G338,0) | Y339: =IF($E338=Y$8,$G338,0) | Z339: =IF($E338=Z$8,$G338,0) | AA339: =IF($E338=AA$8,$G338,0) | ... DA339: =IF($E338=DA$8,$G338,0)
G340: =MARZO!$I340-MARZO!$H340 | N340: =IF($D339="AL",$G339,0) | O340: =IF($D339="BA",$G339,0) | P340: =IF($D339="GF",$G339,0) | Q340: =IF($D339="OT",$G339,0) | R340: =IF($D339="AS",$G339,0) | T340: =IF($E339=T$8,$G339,0) | U340: =IF($E339=U$8,$G339,0) | V340: =IF($E339=V$8,$G339,0) | W340: =IF($E339=W$8,$G339,0) | X340: =IF($E339=X$8,$G339,0) | Y340: =IF($E339=Y$8,$G339,0) | Z340: =IF($E339=Z$8,$G339,0) | AA340: =IF($E339=AA$8,$G339,0) | ... DA340: =IF($E339=DA$8,$G339,0)
G341: =MARZO!$I341-MARZO!$H341 | N341: =IF($D340="AL",$G340,0) | O341: =IF($D340="BA",$G340,0) | P341: =IF($D340="GF",$G340,0) | Q341: =IF($D340="OT",$G340,0) | R341: =IF($D340="AS",$G340,0) | T341: =IF($E340=T$8,$G340,0) | U341: =IF($E340=U$8,$G340,0) | V341: =IF($E340=V$8,$G340,0) | W341: =IF($E340=W$8,$G340,0) | X341: =IF($E340=X$8,$G340,0) | Y341: =IF($E340=Y$8,$G340,0) | Z341: =IF($E340=Z$8,$G340,0) | AA341: =IF($E340=AA$8,$G340,0) | ... DA341: =IF($E340=DA$8,$G340,0)
G342: =MARZO!$I342-MARZO!$H342 | N342: =IF($D341="AL",$G341,0) | O342: =IF($D341="BA",$G341,0) | P342: =IF($D341="GF",$G341,0) | Q342: =IF($D341="OT",$G341,0) | R342: =IF($D341="AS",$G341,0) | T342: =IF($E341=T$8,$G341,0) | U342: =IF($E341=U$8,$G341,0) | V342: =IF($E341=V$8,$G341,0) | W342: =IF($E341=W$8,$G341,0) | X342: =IF($E341=X$8,$G341,0) | Y342: =IF($E341=Y$8,$G341,0) | Z342: =IF($E341=Z$8,$G341,0) | AA342: =IF($E341=AA$8,$G341,0) | ... DA342: =IF($E341=DA$8,$G341,0)
G343: =MARZO!$I343-MARZO!$H343 | N343: =IF($D342="AL",$G342,0) | O343: =IF($D342="BA",$G342,0) | P343: =IF($D342="GF",$G342,0) | Q343: =IF($D342="OT",$G342,0) | R343: =IF($D342="AS",$G342,0) | T343: =IF($E342=T$8,$G342,0) | U343: =IF($E342=U$8,$G342,0) | V343: =IF($E342=V$8,$G342,0) | W343: =IF($E342=W$8,$G342,0) | X343: =IF($E342=X$8,$G342,0) | Y343: =IF($E342=Y$8,$G342,0) | Z343: =IF($E342=Z$8,$G342,0) | AA343: =IF($E342=AA$8,$G342,0) | ... DA343: =IF($E342=DA$8,$G342,0)
G344: =MARZO!$I344-MARZO!$H344 | N344: =IF($D343="AL",$G343,0) | O344: =IF($D343="BA",$G343,0) | P344: =IF($D343="GF",$G343,0) | Q344: =IF($D343="OT",$G343,0) | R344: =IF($D343="AS",$G343,0) | T344: =IF($E343=T$8,$G343,0) | U344: =IF($E343=U$8,$G343,0) | V344: =IF($E343=V$8,$G343,0) | W344: =IF($E343=W$8,$G343,0) | X344: =IF($E343=X$8,$G343,0) | Y344: =IF($E343=Y$8,$G343,0) | Z344: =IF($E343=Z$8,$G343,0) | AA344: =IF($E343=AA$8,$G343,0) | ... DA344: =IF($E343=DA$8,$G343,0)
G345: =MARZO!$I345-MARZO!$H345 | N345: =IF($D344="AL",$G344,0) | O345: =IF($D344="BA",$G344,0) | P345: =IF($D344="GF",$G344,0) | Q345: =IF($D344="OT",$G344,0) | R345: =IF($D344="AS",$G344,0) | T345: =IF($E344=T$8,$G344,0) | U345: =IF($E344=U$8,$G344,0) | V345: =IF($E344=V$8,$G344,0) | W345: =IF($E344=W$8,$G344,0) | X345: =IF($E344=X$8,$G344,0) | Y345: =IF($E344=Y$8,$G344,0) | Z345: =IF($E344=Z$8,$G344,0) | AA345: =IF($E344=AA$8,$G344,0) | ... DA345: =IF($E344=DA$8,$G344,0)
G346: =MARZO!$I346-MARZO!$H346 | N346: =IF($D345="AL",$G345,0) | O346: =IF($D345="BA",$G345,0) | P346: =IF($D345="GF",$G345,0) | Q346: =IF($D345="OT",$G345,0) | R346: =IF($D345="AS",$G345,0) | T346: =IF($E345=T$8,$G345,0) | U346: =IF($E345=U$8,$G345,0) | V346: =IF($E345=V$8,$G345,0) | W346: =IF($E345=W$8,$G345,0) | X346: =IF($E345=X$8,$G345,0) | Y346: =IF($E345=Y$8,$G345,0) | Z346: =IF($E345=Z$8,$G345,0) | AA346: =IF($E345=AA$8,$G345,0) | ... DA346: =IF($E345=DA$8,$G345,0)
G347: =MARZO!$I347-MARZO!$H347 | N347: =IF($D346="AL",$G346,0) | O347: =IF($D346="BA",$G346,0) | P347: =IF($D346="GF",$G346,0) | Q347: =IF($D346="OT",$G346,0) | R347: =IF($D346="AS",$G346,0) | T347: =IF($E346=T$8,$G346,0) | U347: =IF($E346=U$8,$G346,0) | V347: =IF($E346=V$8,$G346,0) | W347: =IF($E346=W$8,$G346,0) | X347: =IF($E346=X$8,$G346,0) | Y347: =IF($E346=Y$8,$G346,0) | Z347: =IF($E346=Z$8,$G346,0) | AA347: =IF($E346=AA$8,$G346,0) | ... DA347: =IF($E346=DA$8,$G346,0)
G348: =MARZO!$I348-MARZO!$H348 | N348: =IF($D347="AL",$G347,0) | O348: =IF($D347="BA",$G347,0) | P348: =IF($D347="GF",$G347,0) | Q348: =IF($D347="OT",$G347,0) | R348: =IF($D347="AS",$G347,0) | T348: =IF($E347=T$8,$G347,0) | U348: =IF($E347=U$8,$G347,0) | V348: =IF($E347=V$8,$G347,0) | W348: =IF($E347=W$8,$G347,0) | X348: =IF($E347=X$8,$G347,0) | Y348: =IF($E347=Y$8,$G347,0) | Z348: =IF($E347=Z$8,$G347,0) | AA348: =IF($E347=AA$8,$G347,0) | ... DA348: =IF($E347=DA$8,$G347,0)
G349: =MARZO!$I349-MARZO!$H349 | N349: =IF($D348="AL",$G348,0) | O349: =IF($D348="BA",$G348,0) | P349: =IF($D348="GF",$G348,0) | Q349: =IF($D348="OT",$G348,0) | R349: =IF($D348="AS",$G348,0) | T349: =IF($E348=T$8,$G348,0) | U349: =IF($E348=U$8,$G348,0) | V349: =IF($E348=V$8,$G348,0) | W349: =IF($E348=W$8,$G348,0) | X349: =IF($E348=X$8,$G348,0) | Y349: =IF($E348=Y$8,$G348,0) | Z349: =IF($E348=Z$8,$G348,0) | AA349: =IF($E348=AA$8,$G348,0) | ... DA349: =IF($E348=DA$8,$G348,0)
... G654: =MARZO!$I654-MARZO!$H654 | N654: =IF($D653="AL",$G653,0) | O654: =IF($D653="BA",$G653,0) | P654: =IF($D653="GF",$G653,0) | Q654: =IF($D653="OT",$G653,0) | R654: =IF($D653="AS",$G653,0) | T654: =IF($E653=T$8,$G653,0) | U654: =IF($E653=U$8,$G653,0) | V654: =IF($E653=V$8,$G653,0) | W654: =IF($E653=W$8,$G653,0) | X654: =IF($E653=X$8,$G653,0) | Y654: =IF($E653=Y$8,$G653,0) | Z654: =IF($E653=Z$8,$G653,0) | AA654: =IF($E653=AA$8,$G653,0) | ... DA654: =IF($E653=DA$8,$G653,0)
B655: Total | G655: =SUBTOTAL(109,MARZO!$G$9:$G$654) | H655: =SUBTOTAL(109,MARZO!$H$9:$H$654) | I655: =SUBTOTAL(109,MARZO!$I$9:$I$654) | N655: =IF($D654="AL",$G654,0) | O655: =IF($D654="BA",$G654,0) | P655: =IF($D654="GF",$G654,0) | Q655: =IF($D654="OT",$G654,0) | R655: =IF($D654="AS",$G654,0) | T655: =IF($E654=T$8,$G654,0) | U655: =IF($E654=U$8,$G654,0) | V655: =IF($E654=V$8,$G654,0) | W655: =IF($E654=W$8,$G654,0) | X655: =IF($E654=X$8,$G654,0) | Y655: =IF($E654=Y$8,$G654,0) | Z655: =IF($E654=Z$8,$G654,0) | AA655: =IF($E654=AA$8,$G654,0) | ... DA655: =IF($E654=DA$8,$G654,0)
N656: =SUM(N9:N655) | O656: =SUM(O9:O655) | P656: =SUM(P9:P655) | Q656: =SUM(Q9:Q655) | R656: =SUM(R9:R655) | T656: =SUM(T9:T655) | U656: =SUM(U9:U655) | V656: =SUM(V9:V655) | W656: =SUM(W9:W655) | X656: =SUM(X9:X655) | Y656: =SUM(Y9:Y655) | Z656: =SUM(Z9:Z655) | AA656: =SUM(AA9:AA655) | ... DA656: =SUM(DA9:DA655) | DB656: =SUM(T656:DA656)
R657: =R656+Q656+P656+O656+N656
B658: ESTADO
B659: =IF(MARZO!$G$655=R657,"BIEN","MAL")
B660: =IF(MARZO!$G$655=DB656,"BIEN","MAL")
