Workbook

Sheet OCTUBRE
C2: RESUMEN | E2: VENTA PERIODO | F2: NETO | G2: % COSTO VENTA | M2: OP | N2: 0.25 | O2: 0.06 | P2: 0.12 | Q2: 0.03 | R2: 0.02
C3: COMERCIAL | F3: =E3/1.19 | G3: =(N6+O6)/F3
C4: VENTA ACTUAL | M4: IND | N4: =IF(N5>N2,"MAL","BIEN") | O4: =IF(O5>O2,"MAL","BIEN") | P4: =IF(P5>P2,"MAL","BIEN") | Q4: =IF(Q5>Q2,"MAL","BIEN") | R4: =IF(R5>R2,"MAL","BIEN")
C5: COSTO VENTA | D5: =N6+O6 | G5: 24 horas | H5: IVA | I5: TOTAL | M5: % | N5: =N6/F3 | O5: =O6/$F$3 | P5: =P6/$F$3 | Q5: =Q6/$F$3 | R5: =R6/$F$3
C6: % COSTO VENTA | D6: =D5/(D4/1.19) | F6: TOTAL ITEM | G6: =OCTUBRE!$G$638 | H6: =OCTUBRE!$H$638 | I6: =OCTUBRE!$I$638 | M6: T | N6: =N638 | O6: =O638 | P6: =P638 | Q6: =Q638 | R6: =R638
B8: DIA | C8: NUM INT | D8: TIPO | E8: PROVEEDOR | F8: NUM FACTURA | G8: SUB TOTAL | H8: IVA | I8: TOTAL | J8: DETALLE | K8: MEDIO PAGO | L8: N CHEQUE | N8: AL | O8: BA | P8: GF | Q8: OT | R8: AS | T8: Abel leal Burgos | U8: Agricola Mamita Paz | V8: Agricola rosario | W8: Agrosuper | X8: Alca | Y8: ALMACENES PARIS | Z8: American pos | AA8: Arenillas | AB8: Atelier | AC8: Aurelia Quezada | AD8: Bastien | AE8: Bredenmaster | AF8: Buen chef | AG8: Carnes Ñuble | AH8: CCU | AI8: Cencosud | AJ8: Central Mayorista | AK8: Chokko | AL8: Coca Cola Andina | AM8: Com. Inver. Chacabuco | AN8: Decaba | AO8: DELMAR | AP8: Desa | AQ8: DIMERC | AR8: EASY | AS8: el taller | AT8: Europapel | AU8: FBS | AV8: FEDERAL SEGURIDAD | AW8: FHM Alimentos | AX8: Fortunata | AY8: Gazpacho | AZ8: Global Frozen | BA8: Gourmet virtual | BB8: Granarolo | BC8: Guallarauco | BD8: Hielo freeze | BE8: Indusmel | BF8: Inversierra | BG8: Isla del faraon | BH8: Jaime Cesar Farias | BI8: Jose Molina | BJ8: Julia del Carmen | BK8: JUMBO | BL8: KITCHEN CENTER SPA | BM8: La Isla del Faraon | BN8: La Vaquita | BO8: La Vinoteca | BP8: Las Delicias del | BQ8: Las piedras | BR8: licores.cl | BS8: Limpicamp Ltda. | BT8: Los colonos | BU8: Mauro | BV8: Mercado Silvestre | BW8: Miguel | BX8: MIGUEL ANGEL PARRA | BY8: Miguel Gonzalez | BZ8: Mimus | CA8: Modus Vivendi | CB8: Neuchatel S.A. | CC8: Nubox | CD8: P&E | CE8: Pahuilmo | CF8: Palta Mundial | CG8: Panesco | CH8: Papeles Santiago | CI8: PC FACTORY | CJ8: Pedidos de hoy | CK8: Pest free | CL8: PF | CM8: Premium Brands | CN8: Productos galdames | CO8: Punto entrega | CP8: PUNTO PLAST | CQ8: RENATE IWERSEN | CR8: Saint Jacques | CS8: Santa Rita | CT8: Servicefood | CU8: silvestre | CV8: Sociedad agricola | CW8: Sofruco | CX8: Southwind | CY8: SURA | CZ8: Surlat | DA8: VCT
G9: =OCTUBRE!$I9-OCTUBRE!$H9 | N9: =IF($D9="AL",$G9,0) | O9: =IF($D9="BA",$G9,0) | P9: =IF($D9="GF",$G9,0) | Q9: =IF($D9="OT",$G9,0) | R9: =IF($D9="AS",$G9,0) | T9: =IF($E9=T$8,$G9,0) | U9: =IF($E9=U$8,$G9,0) | V9: =IF($E9=V$8,$G9,0) | W9: =IF($E9=W$8,$G9,0) | X9: =IF($E9=X$8,$G9,0) | Y9: =IF($E9=Y$8,$G9,0) | Z9: =IF($E9=Z$8,$G9,0) | AA9: =IF($E9=AA$8,$G9,0) | ... DA9: =IF($E9=DA$8,$G9,0)
G10: =OCTUBRE!$I10-OCTUBRE!$H10 | N10: =IF($D10="AL",$G10,0) | O10: =IF($D10="BA",$G10,0) | P10: =IF($D10="GF",$G10,0) | Q10: =IF($D10="OT",$G10,0) | R10: =IF($D10="AS",$G10,0) | T10: =IF($E10=T$8,$G10,0) | U10: =IF($E10=U$8,$G10,0) | V10: =IF($E10=V$8,$G10,0) | W10: =IF($E10=W$8,$G10,0) | X10: =IF($E10=X$8,$G10,0) | Y10: =IF($E10=Y$8,$G10,0) | Z10: =IF($E10=Z$8,$G10,0) | AA10: =IF($E10=AA$8,$G10,0) | ... DA10: =IF($E10=DA$8,$G10,0)
G11: =OCTUBRE!$I11-OCTUBRE!$H11 | N11: =IF($D11="AL",$G11,0) | O11: =IF($D11="BA",$G11,0) | P11: =IF($D11="GF",$G11,0) | Q11: =IF($D11="OT",$G11,0) | R11: =IF($D11="AS",$G11,0) | T11: =IF($E11=T$8,$G11,0) | U11: =IF($E11=U$8,$G11,0) | V11: =IF($E11=V$8,$G11,0) | W11: =IF($E11=W$8,$G11,0) | X11: =IF($E11=X$8,$G11,0) | Y11: =IF($E11=Y$8,$G11,0) | Z11: =IF($E11=Z$8,$G11,0) | AA11: =IF($E11=AA$8,$G11,0) | ... DA11: =IF($E11=DA$8,$G11,0)
G12: =OCTUBRE!$I12-OCTUBRE!$H12 | N12: =IF($D12="AL",$G12,0) | O12: =IF($D12="BA",$G12,0) | P12: =IF($D12="GF",$G12,0) | Q12: =IF($D12="OT",$G12,0) | R12: =IF($D12="AS",$G12,0) | T12: =IF($E12=T$8,$G12,0) | U12: =IF($E12=U$8,$G12,0) | V12: =IF($E12=V$8,$G12,0) | W12: =IF($E12=W$8,$G12,0) | X12: =IF($E12=X$8,$G12,0) | Y12: =IF($E12=Y$8,$G12,0) | Z12: =IF($E12=Z$8,$G12,0) | AA12: =IF($E12=AA$8,$G12,0) | ... DA12: =IF($E12=DA$8,$G12,0)
G13: =OCTUBRE!$I13-OCTUBRE!$H13 | N13: =IF($D13="AL",$G13,0) | O13: =IF($D13="BA",$G13,0) | P13: =IF($D13="GF",$G13,0) | Q13: =IF($D13="OT",$G13,0) | R13: =IF($D13="AS",$G13,0) | T13: =IF($E13=T$8,$G13,0) | U13: =IF($E13=U$8,$G13,0) | V13: =IF($E13=V$8,$G13,0) | W13: =IF($E13=W$8,$G13,0) | X13: =IF($E13=X$8,$G13,0) | Y13: =IF($E13=Y$8,$G13,0) | Z13: =IF($E13=Z$8,$G13,0) | AA13: =IF($E13=AA$8,$G13,0) | ... DA13: =IF($E13=DA$8,$G13,0)
G14: =OCTUBRE!$I14-OCTUBRE!$H14 | N14: =IF($D14="AL",$G14,0) | O14: =IF($D14="BA",$G14,0) | P14: =IF($D14="GF",$G14,0) | Q14: =IF($D14="OT",$G14,0) | R14: =IF($D14="AS",$G14,0) | T14: =IF($E14=T$8,$G14,0) | U14: =IF($E14=U$8,$G14,0) | V14: =IF($E14=V$8,$G14,0) | W14: =IF($E14=W$8,$G14,0) | X14: =IF($E14=X$8,$G14,0) | Y14: =IF($E14=Y$8,$G14,0) | Z14: =IF($E14=Z$8,$G14,0) | AA14: =IF($E14=AA$8,$G14,0) | ... DA14: =IF($E14=DA$8,$G14,0)
G15: =OCTUBRE!$I15-OCTUBRE!$H15 | N15: =IF($D15="AL",$G15,0) | O15: =IF($D15="BA",$G15,0) | P15: =IF($D15="GF",$G15,0) | Q15: =IF($D15="OT",$G15,0) | R15: =IF($D15="AS",$G15,0) | T15: =IF($E15=T$8,$G15,0) | U15: =IF($E15=U$8,$G15,0) | V15: =IF($E15=V$8,$G15,0) | W15: =IF($E15=W$8,$G15,0) | X15: =IF($E15=X$8,$G15,0) | Y15: =IF($E15=Y$8,$G15,0) | Z15: =IF($E15=Z$8,$G15,0) | AA15: =IF($E15=AA$8,$G15,0) | ... DA15: =IF($E15=DA$8,$G15,0)
G16: =OCTUBRE!$I16-OCTUBRE!$H16 | N16: =IF($D16="AL",$G16,0) | O16: =IF($D16="BA",$G16,0) | P16: =IF($D16="GF",$G16,0) | Q16: =IF($D16="OT",$G16,0) | R16: =IF($D16="AS",$G16,0) | T16: =IF($E16=T$8,$G16,0) | U16: =IF($E16=U$8,$G16,0) | V16: =IF($E16=V$8,$G16,0) | W16: =IF($E16=W$8,$G16,0) | X16: =IF($E16=X$8,$G16,0) | Y16: =IF($E16=Y$8,$G16,0) | Z16: =IF($E16=Z$8,$G16,0) | AA16: =IF($E16=AA$8,$G16,0) | ... DA16: =IF($E16=DA$8,$G16,0)
G17: =OCTUBRE!$I17-OCTUBRE!$H17 | N17: =IF($D17="AL",$G17,0) | O17: =IF($D17="BA",$G17,0) | P17: =IF($D17="GF",$G17,0) | Q17: =IF($D17="OT",$G17,0) | R17: =IF($D17="AS",$G17,0) | T17: =IF($E17=T$8,$G17,0) | U17: =IF($E17=U$8,$G17,0) | V17: =IF($E17=V$8,$G17,0) | W17: =IF($E17=W$8,$G17,0) | X17: =IF($E17=X$8,$G17,0) | Y17: =IF($E17=Y$8,$G17,0) | Z17: =IF($E17=Z$8,$G17,0) | AA17: =IF($E17=AA$8,$G17,0) | ... DA17: =IF($E17=DA$8,$G17,0)
G18: =OCTUBRE!$I18-OCTUBRE!$H18 | N18: =IF($D18="AL",$G18,0) | O18: =IF($D18="BA",$G18,0) | P18: =IF($D18="GF",$G18,0) | Q18: =IF($D18="OT",$G18,0) | R18: =IF($D18="AS",$G18,0) | T18: =IF($E18=T$8,$G18,0) | U18: =IF($E18=U$8,$G18,0) | V18: =IF($E18=V$8,$G18,0) | W18: =IF($E18=W$8,$G18,0) | X18: =IF($E18=X$8,$G18,0) | Y18: =IF($E18=Y$8,$G18,0) | Z18: =IF($E18=Z$8,$G18,0) | AA18: =IF($E18=AA$8,$G18,0) | ... DA18: =IF($E18=DA$8,$G18,0)
G19: =OCTUBRE!$I19-OCTUBRE!$H19 | N19: =IF($D19="AL",$G19,0) | O19: =IF($D19="BA",$G19,0) | P19: =IF($D19="GF",$G19,0) | Q19: =IF($D19="OT",$G19,0) | R19: =IF($D19="AS",$G19,0) | T19: =IF($E19=T$8,$G19,0) | U19: =IF($E19=U$8,$G19,0) | V19: =IF($E19=V$8,$G19,0) | W19: =IF($E19=W$8,$G19,0) | X19: =IF($E19=X$8,$G19,0) | Y19: =IF($E19=Y$8,$G19,0) | Z19: =IF($E19=Z$8,$G19,0) | AA19: =IF($E19=AA$8,$G19,0) | ... DA19: =IF($E19=DA$8,$G19,0)
G20: =OCTUBRE!$I20-OCTUBRE!$H20 | N20: =IF($D20="AL",$G20,0) | O20: =IF($D20="BA",$G20,0) | P20: =IF($D20="GF",$G20,0) | Q20: =IF($D20="OT",$G20,0) | R20: =IF($D20="AS",$G20,0) | T20: =IF($E20=T$8,$G20,0) | U20: =IF($E20=U$8,$G20,0) | V20: =IF($E20=V$8,$G20,0) | W20: =IF($E20=W$8,$G20,0) | X20: =IF($E20=X$8,$G20,0) | Y20: =IF($E20=Y$8,$G20,0) | Z20: =IF($E20=Z$8,$G20,0) | AA20: =IF($E20=AA$8,$G20,0) | ... DA20: =IF($E20=DA$8,$G20,0)
... G637: =OCTUBRE!$I637-OCTUBRE!$H637 | N637: =IF($D637="AL",$G637,0) | O637: =IF($D637="BA",$G637,0) | P637: =IF($D637="GF",$G637,0) | Q637: =IF($D637="OT",$G637,0) | R637: =IF($D637="AS",$G637,0) | T637: =IF($E637=T$8,$G637,0) | U637: =IF($E637=U$8,$G637,0) | V637: =IF($E637=V$8,$G637,0) | W637: =IF($E637=W$8,$G637,0) | X637: =IF($E637=X$8,$G637,0) | Y637: =IF($E637=Y$8,$G637,0) | Z637: =IF($E637=Z$8,$G637,0) | AA637: =IF($E637=AA$8,$G637,0) | ... DA637: =IF($E637=DA$8,$G637,0)
B638: Total | G638: =SUBTOTAL(109,OCTUBRE!$G$9:$G$637) | H638: =SUBTOTAL(109,OCTUBRE!$H$9:$H$637) | I638: =SUBTOTAL(109,OCTUBRE!$I$9:$I$637) | N638: =SUM(N9:N637) | O638: =SUM(O9:O637) | P638: =SUM(P9:P637) | Q638: =SUM(Q9:Q637) | R638: =SUM(R9:R637) | T638: =SUM(T9:T637) | U638: =SUM(U9:U637) | V638: =SUM(V9:V637) | W638: =SUM(W9:W637) | X638: =SUM(X9:X637) | Y638: =SUM(Y9:Y637) | Z638: =SUM(Z9:Z637) | AA638: =SUM(AA9:AA637) | ... DA638: =SUM(DA9:DA637) | DB638: =SUM(T638:DA638)
R639: =R638+Q638+P638+O638+N638
B641: ESTADO
B642: =IF(OCTUBRE!$G$638=R639,"BIEN","MAL")
B643: =IF(OCTUBRE!$G$638=DB638,"BIEN","MAL")
